kali_source_updater/__init__.py
kali_source_updater/kali_updater.py
kali_source_updater-1.2.dist-info/LICENSE
kali_source_updater-1.2.dist-info/METADATA
kali_source_updater-1.2.dist-info/WHEEL
kali_source_updater-1.2.dist-info/entry_points.txt
kali_source_updater-1.2.dist-info/top_level.txt
kali_source_updater-1.2.dist-info/RECORD
