Metadata-Version: 2.1
Name: kali-source-updater
Version: 1.2
Summary: A script for updating kali linux source list based on the latency
Home-page: https://github.com/steffinstanly/Kali-Source-Updater
Author: Steffin Stanly
Author-email: steffinstanly@gmail.com
License: UNKNOWN
Platform: UNKNOWN
Classifier: Programming Language :: Python :: 3
Classifier: Programming Language :: Python :: 3.6
Classifier: Programming Language :: Python :: 3.7
Classifier: License :: OSI Approved :: MIT License
Classifier: Operating System :: OS Independent
Requires-Python: >=3.6
Requires-Dist: requests
